CHANGES.txt
CONTRIBUTORS.txt
README.txt
TODO.txt
bootstrap.py
buildout.cfg
setup.py
iw/__init__.py
iw.recipe.cmd.egg-info/PKG-INFO
iw.recipe.cmd.egg-info/SOURCES.txt
iw.recipe.cmd.egg-info/dependency_links.txt
iw.recipe.cmd.egg-info/entry_points.txt
iw.recipe.cmd.egg-info/namespace_packages.txt
iw.recipe.cmd.egg-info/not-zip-safe
iw.recipe.cmd.egg-info/requires.txt
iw.recipe.cmd.egg-info/top_level.txt
iw/recipe/__init__.py
iw/recipe/cmd/README.txt
iw/recipe/cmd/__init__.py
iw/recipe/cmd/test.txt
iw/recipe/cmd/tests/__init__.py
iw/recipe/cmd/tests/test_docs.py
