Metadata-Version: 1.0
Name: iw.recipe.cmd
Version: 0.3
Summary: ZC Buildout recipe to execute a commande line
Home-page: http://plone.org/products/iw-recipes
Author: Ingeniweb
Author-email: support@ingeniweb.com
License: GPL
Keywords: buildout recipe
Platform: UNKNOWN
Classifier: Framework :: Buildout
Classifier: Intended Audience :: Developers
Classifier: Topic :: Software Development :: Build Tools
Classifier: Topic :: Software Development :: Libraries :: Python Modules
Classifier: License :: OSI Approved :: GNU General Public License (GPL)
